degirum_headless.libs/libssl-278540b3.so.1.1
degirum_headless.libs/libcrypto-7f78e54a.so.1.1
degirum/libtflite_runtime_agent_205.dgp
degirum/libonnx_runtime_agent.dgp
degirum/server.py
degirum/compiler.cpython-310-aarch64-linux-gnu.so
degirum/postprocessor.py
degirum/_model_param_helpers.py
degirum/model.py
degirum/_socketio_msgpack.py
degirum/README.md
degirum/log.py
degirum/CoreClient.cpython-310-aarch64-linux-gnu.so
degirum/libmemryx_runtime_agent.dgp
degirum/zoo_manager.py
degirum/libakida_runtime_agent.dgp
degirum/libhailo_runtime_agent--4.19.0.dgp
degirum/LiberationMono-Regular.ttf
degirum/__init__.py
degirum/aiclient.cpython-310-aarch64-linux-gnu.so
degirum/_preprocessor.py
degirum/_zoo_accessor.py
degirum/_filter_models.py
degirum/librknn_runtime_agent.dgp
degirum/exceptions.py
degirum/libtflite_runtime_agent_214.dgp
degirum/pproc_worker.py
degirum/_draw_primitives.py
degirum/libhailo_runtime_agent--4.20.0.dgp
degirum/libtensorrt_runtime_agent.dgp
degirum/libn2x_runtime_agent.dgp
degirum/LICENSES/dotzlib/LICENSE_1_0.txt
degirum/LICENSES/FreeRTOS/LICENSE.md
degirum/LICENSES/hexagon/LICENSE
degirum/LICENSES/cuda/LICENSE
degirum/LICENSES/src/LICENSE.GPL
degirum/LICENSES/wyhash/LICENSE
degirum/LICENSES/ml_dtypes/LICENSE
degirum/LICENSES/ml_dtypes/LICENSE.eigen
degirum/LICENSES/minizip/LICENSE
degirum/LICENSES/crosstool/LICENSE
degirum/LICENSES/flatbuffers/LICENSE.txt
degirum/LICENSES/flatbuffers/LICENSE
degirum/LICENSES/ruy/LICENSE
degirum/LICENSES/zlib/LICENSE
degirum/LICENSES/linuxthreads/LICENSE
degirum/LICENSES/protobuf/LICENSE
degirum/LICENSES/dart/LICENSE
degirum/LICENSES/nccl/LICENSE
degirum/LICENSES/onnx/LICENSE
degirum/LICENSES/generator/LICENSE
degirum/LICENSES/Source/LICENSE.md
degirum/LICENSES/fft2d/LICENSE
degirum/LICENSES/tensorflow214/LICENSE
degirum/LICENSES/googlemock/LICENSE
degirum/LICENSES/FP16/LICENSE
degirum/LICENSES/curl/LICENSE
degirum/LICENSES/sha1/license.txt
degirum_headless-0.15.3.dist-info/RECORD
degirum_headless-0.15.3.dist-info/WHEEL
degirum_headless-0.15.3.dist-info/METADATA
degirum_headless-0.15.3.dist-info/LICENSE
degirum_headless-0.15.3.dist-info/entry_points.txt
degirum_headless-0.15.3.dist-info/top_level.txt
