Metadata-Version: 2.1
Name: degirum-headless
Version: 0.15.3
Summary: DeGirum AI Inference Software Package
Home-page: https://github.com/degirum
Author: DeGirum Corp.
Author-email: support@degirum.com
Classifier: Topic :: Scientific/Engineering :: Artificial Intelligence
Classifier: License :: Freeware
Classifier: Development Status :: 3 - Alpha
Classifier: Programming Language :: Python :: 3
Classifier: License :: Other/Proprietary License
Classifier: Operating System :: Microsoft :: Windows
Requires-Python: >=3.8
License-File: LICENSE
Requires-Dist: pyzmq>=26.1
Requires-Dist: psutil>=6.0
Requires-Dist: pyseccomp>=0.1
Requires-Dist: msgpack<2.0,>=1.0.4
Requires-Dist: msgpack-numpy==0.4.7.1
Requires-Dist: numpy<2.0,>=1.22
Requires-Dist: pillow<11.0,>=9.2
Requires-Dist: python-socketio[client]<6.0,>=5.7
Requires-Dist: pyyaml<7.0,>=6.0
Requires-Dist: types-PyYAML<7.0,>=6.0
Requires-Dist: requests<3.0,>=2.30.0
Requires-Dist: types-requests<3.0,>=2.30.0
Requires-Dist: websocket-client<2.0,>=1.5.1
Requires-Dist: opencv-python-headless<4.11.0.86,>=4.8.0
